setup.py
bin/colorecho
colorecho/__init__.py
colorecho/colorecho.py
colorecho.egg-info/PKG-INFO
colorecho.egg-info/SOURCES.txt
colorecho.egg-info/dependency_links.txt
colorecho.egg-info/top_level.txt