Metadata-Version: 1.1
Name: colorecho
Version: 0.1
Summary: Wrap your strings in terminal color codes. From a terminal command.
Home-page: https://github.com/mahyar/colorecho
Author: Mahyar McDonald
Author-email: no.email@example.com
License: MIT
Platform: UNKNOWN
Classifier: Development Status :: 5 - Production/Stable
Classifier: Environment :: Console
Classifier: License :: OSI Approved :: MIT License
Classifier: Programming Language :: Python :: 3
Classifier: Programming Language :: Python :: 2
